mcp_proto_okn/__init__.py
mcp_proto_okn/server.py
mcp_proto_okn/server_mod1.py
mcp_proto_okn/server_mod10.py
mcp_proto_okn/server_mod11.py
mcp_proto_okn/server_mod2.py
mcp_proto_okn/server_mod3.py
mcp_proto_okn/server_mod4.py
mcp_proto_okn/server_mod5.py
mcp_proto_okn/server_mod6.py
mcp_proto_okn/server_mod6a.py
mcp_proto_okn/server_mod7.py
mcp_proto_okn/server_mod8.py
mcp_proto_okn/server_mod9.py
mcp_proto_okn-0.5.0.dist-info/METADATA
mcp_proto_okn-0.5.0.dist-info/WHEEL
mcp_proto_okn-0.5.0.dist-info/entry_points.txt
mcp_proto_okn-0.5.0.dist-info/licenses/LICENSE
mcp_proto_okn-0.5.0.dist-info/RECORD
