Metadata-Version: 2.4
Name: mcp-proto-okn
Version: 0.5.0
Summary: MCP server for querying FRINK SPARKQL endpoints, a project by the NSF Prototype Open Knowledge Network (Proto-OKN) program.
Project-URL: Homepage, https://github.com/sbl-sdsc/mcp-proto-okn
Project-URL: Repository, https://github.com/sbl-sdsc/mcp-proto-okn
Project-URL: Issues, https://github.com/sbl-sdsc/mcp-proto-okn/issues
Author-email: Peter W Rose <pwrose.ucsd@gmail.com>, Eric Zhu <ekzhu@users.noreply.github.com>
License: BSD-3-Clause
License-File: LICENSE
Keywords: frink,knowledge graphs,mcp,proto-okn,sparql
Classifier: Development Status :: 4 - Beta
Classifier: Intended Audience :: Developers
Classifier: License :: OSI Approved :: BSD License
Classifier: Programming Language :: Python :: 3.10
Classifier: Programming Language :: Python :: 3.11
Classifier: Programming Language :: Python :: 3.12
Requires-Python: >=3.10
Requires-Dist: certifi>=2024.0.0
Requires-Dist: mcp>=1.6.0
Requires-Dist: sparqlwrapper>=2.0.0
Provides-Extra: cli
Requires-Dist: mcp[cli]; extra == 'cli'
Requires-Dist: typer>=0.12; extra == 'cli'
